{
  "apple_official_colors": {
    "iphone_17_pro": {
      "product": "iPhone 17 Pro / Pro Max",
      "material": "Aluminum unibody",
      "colors": [
        {
          "name": "Cosmic Orange",
          "official_name": "Cosmic Orange",
          "description": "Bold, fluorescent orange with warm undertones. A striking departure from traditional Pro colors.",
          "hex": "#FF6B35",
          "gradient": "linear-gradient(135deg, #FF6B35 0%, #C44D34 100%)",
          "notes": "First vibrant color for Pro models in years. May also be described as 'Dark Gold' or 'Copper'."
        },
        {
          "name": "Deep Blue",
          "official_name": "Deep Blue",
          "description": "Rich, deep blue similar to Mood Indigo (Pantone 19-4025 TPG). Professional and sophisticated.",
          "hex": "#1E3A5F",
          "gradient": "linear-gradient(135deg, #1E3A5F 0%, #0A1929 100%)",
          "notes": "Replaces the lighter blues from previous generations. Similar to Blue Titanium but adapted for aluminum."
        },
        {
          "name": "Silver",
          "official_name": "Silver",
          "description": "Classic silver metallic finish. Clean, professional, and timeless.",
          "hex": "#E8E8E8",
          "gradient": "linear-gradient(135deg, #E8E8E8 0%, #C0C0C0 100%)",
          "notes": "Staple color for Pro models."
        }
      ]
    },
    "iphone_17": {
      "product": "iPhone 17",
      "material": "Aluminum with glass back",
      "colors": [
        {
          "name": "Black",
          "official_name": "Black",
          "description": "Very dark gray, nearly black. Classic and understated.",
          "hex": "#1C1C1E",
          "gradient": "linear-gradient(135deg, #1C1C1E 0%, #000000 100%)",
          "notes": "Not pure black, more of a dark charcoal gray."
        },
        {
          "name": "White",
          "official_name": "White",
          "description": "Clean, bright white with subtle warmth.",
          "hex": "#F5F5F0",
          "gradient": "linear-gradient(135deg, #F5F5F0 0%, #FFFFFF 100%)",
          "notes": "Timeless, minimalist choice."
        },
        {
          "name": "Lavender",
          "official_name": "Lavender",
          "description": "Light purple/lavender shade, darker than iPhone 14's purple.",
          "hex": "#E6D5E8",
          "gradient": "linear-gradient(135deg, #E6D5E8 0%, #D4C5F9 100%)",
          "notes": "Returns after being replaced by pink in iPhone 15/16."
        },
        {
          "name": "Light Blue",
          "official_name": "Light Blue",
          "description": "Soft, pastel blue similar to iPhone 15 Blue but slightly richer.",
          "hex": "#A8D8EA",
          "gradient": "linear-gradient(135deg, #A8D8EA 0%, #87CEEB 100%)",
          "notes": "Softer than Ultramarine, more saturated than iPhone 15."
        },
        {
          "name": "Sage",
          "official_name": "Sage",
          "description": "Muted green with gray undertones.",
          "hex": "#9CAF88",
          "gradient": "linear-gradient(135deg, #9CAF88 0%, #8B9A7A 100%)",
          "notes": "Subtle, natural-looking green."
        },
        {
          "name": "Steel Gray",
          "official_name": "Steel Gray",
          "description": "Medium gray with cool undertones.",
          "hex": "#8B8D8F",
          "gradient": "linear-gradient(135deg, #8B8D8F 0%, #6D6E70 100%)",
          "notes": "Modern take on Space Gray. Availability may vary."
        }
      ]
    },
    "iphone_17_air": {
      "product": "iPhone 17 Air",
      "material": "Ultra-thin aluminum design",
      "colors": [
        {
          "name": "Sky Blue",
          "official_name": "Sky Blue",
          "description": "Light, airy blue - lighter than iPhone 17's blue. Matches M4 MacBook Air.",
          "hex": "#87CEEB",
          "gradient": "linear-gradient(135deg, #87CEEB 0%, #4A90E2 100%)",
          "notes": "Designed to emphasize the lightness of the device (145g, 5.5mm thin)."
        },
        {
          "name": "Gardenia",
          "official_name": "Gardenia",
          "description": "Soft cream/beige color, lighter version of Desert Titanium.",
          "hex": "#F5E6D3",
          "gradient": "linear-gradient(135deg, #F5E6D3 0%, #E8D5C0 100%)",
          "notes": "Warm, elegant neutral tone."
        },
        {
          "name": "Black",
          "official_name": "Black",
          "description": "Classic black finish.",
          "hex": "#1C1C1E",
          "gradient": "linear-gradient(135deg, #1C1C1E 0%, #000000 100%)",
          "notes": "Standard option."
        },
        {
          "name": "White",
          "official_name": "White",
          "description": "Pure white finish.",
          "hex": "#FFFFFF",
          "gradient": "linear-gradient(135deg, #FFFFFF 0%, #F5F5F0 100%)",
          "notes": "Clean, minimalist option."
        }
      ]
    },
    "iphone_16_plus": {
      "product": "iPhone 16 / iPhone 16 Plus",
      "material": "Aluminum with glass back",
      "colors": [
        {
          "name": "Black",
          "official_name": "Black",
          "description": "Deep, almost-black shade. Sleek and professional.",
          "hex": "#1C1C1E",
          "gradient": "linear-gradient(135deg, #1C1C1E 0%, #000000 100%)",
          "notes": "Very similar to iPhone 15 Black."
        },
        {
          "name": "White",
          "official_name": "White",
          "description": "Warm white, elegant and simple.",
          "hex": "#F5F5F0",
          "gradient": "linear-gradient(135deg, #F5F5F0 0%, #FFFFFF 100%)",
          "notes": "Not offered on iPhone 15, making a return."
        },
        {
          "name": "Pink",
          "official_name": "Pink",
          "description": "Bright, vibrant pink - bolder than iPhone 15's soft pink.",
          "hex": "#FFB6C1",
          "gradient": "linear-gradient(135deg, #FFB6C1 0%, #FF69B4 100%)",
          "notes": "Most eye-catching color. Very different from previous years' pastels."
        },
        {
          "name": "Teal",
          "official_name": "Teal",
          "description": "Deep teal/aqua green, more saturated than iPhone 15 Green.",
          "hex": "#008B8B",
          "gradient": "linear-gradient(135deg, #008B8B 0%, #006666 100%)",
          "notes": "Perfect for water/beach aesthetic. Avoids being too green."
        },
        {
          "name": "Ultramarine",
          "official_name": "Ultramarine",
          "description": "Deep, vibrant blue - much bolder than iPhone 15 Blue.",
          "hex": "#120A8F",
          "gradient": "linear-gradient(135deg, #120A8F 0%, #000080 100%)",
          "notes": "Most popular new color. Deep sea/indigo vibe."
        }
      ]
    },
    "iphone_16_pro": {
      "product": "iPhone 16 Pro / Pro Max",
      "material": "Grade 5 Titanium",
      "colors": [
        {
          "name": "Black Titanium",
          "official_name": "Black Titanium",
          "description": "Darker than iPhone 15 Pro's Black Titanium. Nearly pure black.",
          "hex": "#1C1C1E",
          "gradient": "linear-gradient(135deg, #1C1C1E 0%, #000000 100%)",
          "notes": "New Grade 5 titanium makes it darker than previous generation."
        },
        {
          "name": "Natural Titanium",
          "official_name": "Natural Titanium",
          "description": "Light gray, cleaner looking than iPhone 15 Pro version.",
          "hex": "#E0E0E0",
          "gradient": "linear-gradient(135deg, #E0E0E0 0%, #C0C0C0 100%)",
          "notes": "Most popular neutral option. Lighter than previous gen."
        },
        {
          "name": "White Titanium",
          "official_name": "White Titanium",
          "description": "Brighter white with cooler undertones than iPhone 15 Pro.",
          "hex": "#F5F5F5",
          "gradient": "linear-gradient(135deg, #F5F5F5 0%, #E8E8E8 100%)",
          "notes": "Cleaner, more refined than previous White Titanium."
        },
        {
          "name": "Desert Titanium",
          "official_name": "Desert Titanium",
          "description": "Beige-gold variant with warm tones. Signature color for 16 Pro.",
          "hex": "#D4B896",
          "gradient": "linear-gradient(135deg, #D4B896 0%, #C4A880 100%)",
          "notes": "Replaces Blue Titanium. Warmer frame contrasts with softer back."
        }
      ]
    },
    "macbook_air_m4": {
      "product": "MacBook Air 13\" & 15\" (M4)",
      "material": "Recycled aluminum unibody",
      "colors": [
        {
          "name": "Midnight",
          "official_name": "Midnight",
          "description": "Very dark blue-black finish with anodized aluminum.",
          "hex": "#191970",
          "gradient": "linear-gradient(135deg, #191970 0%, #0A0A28 100%)",
          "notes": "Most popular color. Deep, rich finish. May show fingerprints."
        },
        {
          "name": "Starlight",
          "official_name": "Starlight",
          "description": "Champagne gold/rose gold with warm undertones.",
          "hex": "#F5F5DC",
          "gradient": "linear-gradient(135deg, #F5F5DC 0%, #E8E8D0 100%)",
          "notes": "Warm, elegant neutral. Similar to rose gold but more subdued."
        },
        {
          "name": "Silver",
          "official_name": "Silver",
          "description": "Classic silver aluminum finish.",
          "hex": "#E8E8E8",
          "gradient": "linear-gradient(135deg, #E8E8E8 0%, #C0C0C0 100%)",
          "notes": "Traditional Mac color. Professional and timeless."
        },
        {
          "name": "Sky Blue",
          "official_name": "Sky Blue",
          "description": "NEW 2025! Metallic light blue, similar to iPhone 17 Air's Sky Blue.",
          "hex": "#87CEEB",
          "gradient": "linear-gradient(135deg, #87CEEB 0%, #4A90E2 100%)",
          "notes": "First appearance: March 2025. Not as bright as iMac's blue."
        }
      ]
    },
    "ipad_pro_m5": {
      "product": "iPad Pro 11\" & 13\" (M5)",
      "material": "Aluminum unibody, ultra-thin design",
      "colors": [
        {
          "name": "Space Black",
          "official_name": "Space Black",
          "description": "Deep black/dark gray finish.",
          "hex": "#2C2C2E",
          "gradient": "linear-gradient(135deg, #2C2C2E 0%, #1C1C1E 100%)",
          "notes": "Professional, modern finish. Available in standard and nano-texture glass."
        },
        {
          "name": "Silver",
          "official_name": "Silver",
          "description": "Bright silver aluminum finish.",
          "hex": "#E8E8E8",
          "gradient": "linear-gradient(135deg, #E8E8E8 0%, #C0C0C0 100%)",
          "notes": "Classic iPad Pro color. Available in standard and nano-texture glass."
        }
      ]
    }
  },
  "color_naming_conventions": {
    "apple_naming_patterns": {
      "pro_devices": "Tend to use material names (Titanium, Space Black) or minimal descriptors",
      "consumer_devices": "Use more creative, evocative names (Cosmic Orange, Ultramarine, Sky Blue)",
      "recent_trends": "Apple moving toward bolder colors after years of muted pastels (2024-2025)"
    },
    "material_finishes": {
      "aluminum": "Used in MacBook Air, iPhone 17 series, standard iPhones",
      "titanium": "Premium material for iPhone Pro models (2023-2024)",
      "glass": "Used for iPhone backs, available in glossy and nano-texture"
    }
  },
  "color_history_notes": {
    "iphone": {
      "trend_2024": "Extremely muted, pastel colors (iPhone 15)",
      "trend_2025": "Return to vibrant, saturated colors (iPhone 16, 17)",
      "pro_evolution": "Moved from stainless steel to titanium (2023), then aluminum (2025)"
    },
    "macbook": {
      "discontinued_2025": "Space Gray replaced by Sky Blue in M4 Air",
      "color_consistency": "Midnight, Starlight, Silver remain across generations"
    },
    "ipad": {
      "pro_minimalism": "iPad Pro keeps only 2 colors (Space Black, Silver)",
      "air_variety": "iPad Air offers more color options"
    }
  },
  "hex_color_notes": {
    "disclaimer": "Hex values are approximate representations based on official images and descriptions. Actual colors may vary based on lighting, display calibration, and manufacturing variations.",
    "material_impact": "Aluminum, titanium, and glass finishes reflect light differently, affecting perceived color.",
    "best_practices": "Always reference official Apple product images for the most accurate color representation."
  },
  "usage_recommendations": {
    "for_ecommerce": "Use official color names in product listings",
    "for_design": "Reference hex codes as starting points, adjust based on material",
    "for_inventory": "Include year and model for color disambiguation (e.g., 'Silver iPhone 16 Pro' vs 'Silver MacBook Air M4')"
  }
}
